pyeplan/__init__.py
pyeplan/dataproc.py
pyeplan/investoper.py
pyeplan/routing.py
pyeplan-1.1.4.dist-info/licenses/LICENSE.txt
pyeplan-1.1.4.dist-info/METADATA
pyeplan-1.1.4.dist-info/WHEEL
pyeplan-1.1.4.dist-info/top_level.txt
pyeplan-1.1.4.dist-info/RECORD
