Metadata-Version: 2.4
Name: pyeplan
Version: 1.1.4
Summary: Python library for planning and operation of resilient microgrids.
Author-email: Shahab Dehghan <s.dehghan@ieee.org>, Agnes Nakiganda <a.m.nakiganda@gmail.com>, Petros Aristidou <petros.aristidou@cut.ac.cy>
License: Apache Software License
Project-URL: Homepage, https://pyeplan.sps-lab.org
Project-URL: Documentation, https://pyeplan.sps-lab.org
Project-URL: Repository, https://github.com/SPS-L/pyeplan
Project-URL: Bug Tracker, https://github.com/SPS-L/pyeplan/issues
Project-URL: Source, https://github.com/SPS-L/pyeplan
Keywords: energy,planning,microgrids,optimization,resilience,power-systems
Classifier: Development Status :: 5 - Production/Stable
Classifier: Intended Audience :: Science/Research
Classifier: Intended Audience :: Developers
Classifier: License :: OSI Approved :: Apache Software License
Classifier: Operating System :: OS Independent
Classifier: Programming Language :: Python :: 3
Classifier: Programming Language :: Python :: 3.7
Classifier: Programming Language :: Python :: 3.8
Classifier: Programming Language :: Python :: 3.9
Classifier: Programming Language :: Python :: 3.10
Classifier: Programming Language :: Python :: 3.11
Classifier: Topic :: Scientific/Engineering
Classifier: Topic :: Scientific/Engineering :: Mathematics
Classifier: Topic :: Software Development :: Libraries :: Python Modules
Requires-Python: >=3.7
License-File: LICENSE.txt
Requires-Dist: pandas<2.0.0,>=1.3.4
Requires-Dist: pyomo<7.0.0,>=6.1.2
Requires-Dist: networkx<3.0.0,>=2.6.3
Requires-Dist: matplotlib<4.0.0,>=3.3.0
Requires-Dist: timezonefinder<6.0.0,>=5.2.0
Requires-Dist: scikit-learn<2.0.0,>=1.0.0
Requires-Dist: openpyxl<4.0.0,>=3.0.9
Requires-Dist: ipython<9.0.0,>=7.0.0
Requires-Dist: folium<1.0.0,>=0.12.0
Requires-Dist: numpy<2.0.0,>=1.21.0
Requires-Dist: jupyter<2.0.0,>=1.0.0
Dynamic: license-file
